odoo/addons/base_ubl_payment/README.rst
odoo/addons/base_ubl_payment/__init__.py
odoo/addons/base_ubl_payment/__manifest__.py
odoo/addons/base_ubl_payment/i18n/base_ubl_payment.pot
odoo/addons/base_ubl_payment/i18n/nl_NL.po
odoo/addons/base_ubl_payment/models/__init__.py
odoo/addons/base_ubl_payment/models/ubl.py
odoo/addons/base_ubl_payment/readme/CONTRIBUTORS.rst
odoo/addons/base_ubl_payment/readme/DESCRIPTION.rst
odoo/addons/base_ubl_payment/static/description/icon.png
odoo/addons/base_ubl_payment/static/description/index.html
odoo11_addon_base_ubl_payment-11.0.1.0.0.99.dev9.dist-info/METADATA
odoo11_addon_base_ubl_payment-11.0.1.0.0.99.dev9.dist-info/WHEEL
odoo11_addon_base_ubl_payment-11.0.1.0.0.99.dev9.dist-info/top_level.txt
odoo11_addon_base_ubl_payment-11.0.1.0.0.99.dev9.dist-info/RECORD
